rcsb/__init__.py
rcsb/utils/__init__.py
rcsb/utils/dictionary/DictMethodAssemblyHelper.py
rcsb/utils/dictionary/DictMethodChemRefHelper.py
rcsb/utils/dictionary/DictMethodCommonUtils.py
rcsb/utils/dictionary/DictMethodEntityHelper.py
rcsb/utils/dictionary/DictMethodEntityInstanceHelper.py
rcsb/utils/dictionary/DictMethodEntryHelper.py
rcsb/utils/dictionary/DictMethodResourceCacheWorkflow.py
rcsb/utils/dictionary/DictMethodResourceProvider.py
rcsb/utils/dictionary/DictMethodRunner.py
rcsb/utils/dictionary/DictionaryApiProvider.py
rcsb/utils/dictionary/DictionaryApiProviderWrapper.py
rcsb/utils/dictionary/NeighborInteractionProvider.py
rcsb/utils/dictionary/NeighborInteractionWorkflow.py
rcsb/utils/dictionary/__init__.py
rcsb.utils.dictionary-0.61.dist-info/LICENSE
rcsb.utils.dictionary-0.61.dist-info/METADATA
rcsb.utils.dictionary-0.61.dist-info/WHEEL
rcsb.utils.dictionary-0.61.dist-info/top_level.txt
rcsb.utils.dictionary-0.61.dist-info/RECORD
