Metadata-Version: 2.1
Name: rcsb.utils.dictionary
Version: 0.61
Summary: RCSB Python Dictionary Utility Classes
Home-page: https://github.com/rcsb/py-rcsb_utils_dictionary
Author: John Westbrook
Author-email: john.westbrook@rcsb.org
License: Apache 2.0
Platform: UNKNOWN
Classifier: Development Status :: 3 - Alpha
Classifier: Intended Audience :: Developers
Classifier: Natural Language :: English
Classifier: License :: OSI Approved :: Apache Software License
Classifier: Programming Language :: Python
Classifier: Programming Language :: Python :: 3
Classifier: Programming Language :: Python :: 3.9
Requires-Dist: scipy
Requires-Dist: numpy
Requires-Dist: mmcif (>=0.71)
Requires-Dist: rcsb.utils.chemref (>=0.79)
Requires-Dist: rcsb.utils.citation (>=0.16)
Requires-Dist: rcsb.utils.config (>=0.35)
Requires-Dist: rcsb.utils.ec (>=0.22)
Requires-Dist: rcsb.utils.io (>=1.16)
Requires-Dist: rcsb.utils.multiproc (>=0.18)
Requires-Dist: rcsb.utils.repository (>=0.16)
Requires-Dist: rcsb.utils.seq (>=0.63)
Requires-Dist: rcsb.utils.struct (>=0.32)
Requires-Dist: rcsb.utils.targets (>=0.56)
Requires-Dist: rcsb.utils.taxonomy (>=0.39)
Requires-Dist: rcsb.utils.validation (>=0.22)
Provides-Extra: dev
Requires-Dist: check-manifest ; extra == 'dev'
Provides-Extra: test
Requires-Dist: coverage ; extra == 'test'
